{
  "analysis_id": "52981861-a1e4-4e46-a398-627bad64a873",
  "status": "success",
  "created_at": "2026-03-07T16:21:46.943813",
  "results": [
    {
      "note_id": "68ad2e3f000000001c03d209",
      "title": "七夕种草！一键让胶佬理解口红段位",
      "makeup_style": [
        "韩系妆容"
      ],
      "lipstick_features": {
        "color": "珊瑚橘",
        "texture": "丝绒雾面",
        "saturation": "中饱和",
        "tone": "暖调"
      },
      "keywords": [
        "显白",
        "不拔干",
        "日常"
      ],
      "scene": [
        "约会",
        "日常通勤"
      ]
    },
    {
      "note_id": "684d5373000000002301d585",
      "title": "长期主义 大四女生 大牌口红分享💄",
      "makeup_style": [
        "韩系妆容",
        "复古风"
      ],
      "lipstick_features": {
        "color": "珊瑚橘",
        "texture": "丝绒雾面",
        "saturation": "中饱和",
        "tone": "暖调"
      },
      "keywords": [
        "显白",
        "不拔干",
        "日常"
      ],
      "scene": [
        "约会",
        "日常通勤"
      ]
    },
    {
      "note_id": "68bec897000000001b020917",
      "title": "大学生第一支大牌口红选什么🤔",
      "makeup_style": [
        "韩系妆容",
        "复古风"
      ],
      "lipstick_features": {
        "color": "珊瑚橘",
        "texture": "丝绒雾面",
        "saturation": "中饱和",
        "tone": "暖调"
      },
      "keywords": [
        "显白",
        "不拔干",
        "日常"
      ],
      "scene": [
        "约会",
        "日常通勤"
      ]
    },
    {
      "note_id": "6893692b0000000022021579",
      "title": "mark5️⃣支大牌💄！很天菜的级别！！",
      "makeup_style": [
        "韩系妆容",
        "复古风"
      ],
      "lipstick_features": {
        "color": "珊瑚橘",
        "texture": "丝绒雾面",
        "saturation": "中饱和",
        "tone": "暖调"
      },
      "keywords": [
        "显白",
        "不拔干",
        "日常"
      ],
      "scene": [
        "约会",
        "日常通勤"
      ]
    },
    {
      "note_id": "68bc45e5000000001d0158f6",
      "title": "裸粉，裸棕，还是裸橘？裸色口红大起底！",
      "makeup_style": [
        "韩系妆容"
      ],
      "lipstick_features": {
        "color": "裸橘",
        "texture": "水润",
        "saturation": "中饱和",
        "tone": "暖调"
      },
      "keywords": [
        "显白",
        "自然感",
        "气质"
      ],
      "scene": [
        "约会",
        "日常通勤"
      ]
    },
    {
      "note_id": "696f34ac000000000d00a2f5",
      "title": "2025🤍我的年度18图",
      "makeup_style": [
        "韩系妆容"
      ],
      "lipstick_features": {
        "color": "樱花粉",
        "texture": "水润",
        "saturation": "中饱和",
        "tone": "暖调"
      },
      "keywords": [
        "显白",
        "水润",
        "自然清透"
      ],
      "scene": [
        "约会",
        "日常通勤"
      ]
    },
    {
      "note_id": "69280750000000000d03d7e0",
      "title": "西安旅游?约会? 分享几组妆容放大你的美",
      "makeup_style": [
        "韩系妆容",
        "复古风"
      ],
      "lipstick_features": {
        "color": "珊瑚橘",
        "texture": "丝绒雾面",
        "saturation": "中饱和",
        "tone": "暖调"
      },
      "keywords": [
        "显白",
        "不拔干",
        "日常"
      ],
      "scene": [
        "约会",
        "日常通勤"
      ]
    },
    {
      "note_id": "69395eb3000000001e03814a",
      "title": "肿眼泡来化金智羽的美萌灵动感消肿妆 ！",
      "makeup_style": [
        "韩系妆容",
        "自然裸妆"
      ],
      "lipstick_features": {
        "color": "珊瑚橘",
        "texture": "水润",
        "saturation": "中饱和",
        "tone": "暖调"
      },
      "keywords": [
        "显白",
        "不晕染",
        "清透"
      ],
      "scene": [
        "约会",
        "日常通勤"
      ]
    },
    {
      "note_id": "68c815a8000000001d036be2",
      "title": "我愿称之为现实万能神妆…",
      "makeup_style": [
        "韩系妆容"
      ],
      "lipstick_features": {
        "color": "珊瑚橘",
        "texture": "水润",
        "saturation": "中饱和",
        "tone": "暖调"
      },
      "keywords": [
        "显白",
        "不拔干",
        "日常"
      ],
      "scene": [
        "约会",
        "日常通勤"
      ]
    },
    {
      "note_id": "6964ec9b0000000022030522",
      "title": "巨详细跟练｜方圆脸快试试古早甜妹妆！",
      "makeup_style": [
        "韩系妆容",
        "复古风"
      ],
      "lipstick_features": {
        "color": "珊瑚橘",
        "texture": "丝绒雾面",
        "saturation": "中饱和",
        "tone": "暖调"
      },
      "keywords": [
        "显白",
        "不拔干",
        "日常"
      ],
      "scene": [
        "约会",
        "日常通勤"
      ]
    }
  ],
  "statistics": {
    "total_notes": 10,
    "analyzed_notes": 10,
    "failed_notes": 0,
    "styles": [
      {
        "name": "韩系妆容",
        "count": 10,
        "percentage": 100.0
      },
      {
        "name": "复古风",
        "count": 5,
        "percentage": 50.0
      },
      {
        "name": "自然裸妆",
        "count": 1,
        "percentage": 10.0
      }
    ],
    "colors": [
      {
        "name": "珊瑚橘",
        "count": 8,
        "percentage": 80.0
      },
      {
        "name": "裸橘",
        "count": 1,
        "percentage": 10.0
      },
      {
        "name": "樱花粉",
        "count": 1,
        "percentage": 10.0
      }
    ],
    "keywords": [
      {
        "name": "显白",
        "count": 10
      },
      {
        "name": "不拔干",
        "count": 7
      },
      {
        "name": "日常",
        "count": 7
      },
      {
        "name": "自然感",
        "count": 1
      },
      {
        "name": "气质",
        "count": 1
      },
      {
        "name": "水润",
        "count": 1
      },
      {
        "name": "自然清透",
        "count": 1
      },
      {
        "name": "不晕染",
        "count": 1
      },
      {
        "name": "清透",
        "count": 1
      }
    ]
  },
  "report": {
    "report_title": "化妆风格与色彩分析报告",
    "summary": "本报告对10组化妆笔记进行了全面分析，重点探讨了化妆风格与色彩的分布情况。结果显示，韩系妆容在所有笔记中占据绝对主导地位，结果呈现出强烈的流行趋势。此外，珊瑚橘色调的使用频率最高，展现出其受欢迎程度。关键词分析亦揭示了消费者偏好的重要特征，特别是在自然感和日常使用的追求上。",
    "sections": [
      {
        "section_id": "section-1",
        "title": "化妆风格分布",
        "content": "在本次化妆风格分布分析中，我们的数据显示，韩系妆容占据了绝对主导地位，所有样本中出现频率高达100%。这一点凸显了韩系妆容在当前化妆趋势中的强劲影响力。其以自然清新的肤色、精致的眼妆以及粉嫩的唇色为特色，符合年轻消费者对美丽的定义。这一现象也反映出消费者对于日常通勤和社交场合中自然妆感的需求日益增加。\n\n进一步分析，复古风妆容在样本中的占比为50%，显示出这一风格正逐渐受到追捧。复古妆容往往带有较强的个性化特征和文化内涵，能够引发用户对往年流行风潮的怀旧情感。这一趋势可能与当代年轻人对个性表达和时尚多样性的追求相契合，同时也可能受到社交媒体及流行文化的推动。\n\n而自然裸妆的出现率明显较低，仅为10%。虽然这一风格在某些特定消费者群体中仍有其市场，但长久以来其隐秘性及对妆容技巧的要求，限制了其在广泛受众中的认可度。因此，对于品牌而言，在推广新产品时，可以考虑围绕韩系妆容展开，通过社交平台进行有效传播，而对于复古风妆容，可以更多地借助潮流事件来吸引目标受众的关注。建议品牌在产品设计与市场推介上，注重结合这两大流行趋势，挖掘更多可持续的创意。",
        "charts": [
          {
            "chart_type": "pie",
            "chart_title": "化妆风格占比",
            "description": "显示各化妆风格在笔记中的占比情况",
            "echarts_option": {
              "tooltip": {
                "trigger": "item",
                "formatter": "{a} <br/>{b}: {c} ({d}%)"
              },
              "legend": {
                "orient": "vertical",
                "left": "left",
                "top": "center"
              },
              "series": [
                {
                  "name": "化妆风格占比",
                  "type": "pie",
                  "radius": [
                    "40%",
                    "70%"
                  ],
                  "center": [
                    "50%",
                    "50%"
                  ],
                  "data": [
                    {
                      "name": "韩系妆容",
                      "value": 10
                    },
                    {
                      "name": "复古风",
                      "value": 5
                    },
                    {
                      "name": "自然裸妆",
                      "value": 1
                    }
                  ],
                  "label": {
                    "show": true,
                    "position": "outside",
                    "formatter": "{b}: {c} ({d}%)"
                  },
                  "itemStyle": {
                    "borderRadius": 5,
                    "borderWidth": 2,
                    "borderColor": "#fff"
                  }
                }
              ],
              "color": [
                "#ff6b9d",
                "#5f27cd",
                "#00d2d3",
                "#feca57",
                "#ee5a6f",
                "#48dbfb",
                "#ff9ff3",
                "#54a0ff"
              ]
            }
          },
          {
            "chart_type": "bar",
            "chart_title": "化妆风格数量对比",
            "description": "对比不同化妆风格的数量",
            "echarts_option": {
              "tooltip": {
                "trigger": "axis",
                "axisPointer": {
                  "type": "shadow"
                }
              },
              "grid": {
                "left": "3%",
                "right": "4%",
                "bottom": "3%",
                "containLabel": true
              },
              "xAxis": {
                "type": "category",
                "data": [
                  "韩系妆容",
                  "复古风",
                  "自然裸妆"
                ],
                "axisLabel": {
                  "show": true
                },
                "axisLine": {
                  "show": true
                }
              },
              "yAxis": {
                "type": "value",
                "data": null
              },
              "series": [
                {
                  "name": "数量",
                  "type": "bar",
                  "data": [
                    10,
                    5,
                    1
                  ],
                  "barWidth": "60%",
                  "itemStyle": {
                    "color": {
                      "type": "linear",
                      "x": 0,
                      "y": 0,
                      "x2": 0,
                      "y2": 1,
                      "colorStops": [
                        {
                          "offset": 0,
                          "color": "#ff6b9d"
                        },
                        {
                          "offset": 1,
                          "color": "#48dbfb"
                        }
                      ]
                    }
                  },
                  "label": {
                    "show": true,
                    "position": "top"
                  }
                }
              ],
              "color": [
                "#ff6b9d",
                "#5f27cd",
                "#00d2d3",
                "#feca57",
                "#ee5a6f",
                "#48dbfb",
                "#ff9ff3",
                "#54a0ff"
              ]
            }
          }
        ],
        "order": 1
      },
      {
        "section_id": "section-2",
        "title": "色彩使用情况",
        "content": "在本次色彩使用情况的分析中，珊瑚橘色调显然主导了市场，占据了80%的使用比例。这一色彩的受欢迎程度可能与其所带来的温暖和活力形象有关，尤其是在春夏季节，珊瑚橘常常与轻松、愉悦的心情联结在一起。因此，在产品开发和市场推广中，品牌可考虑加大对珊瑚橘系列的投入，以满足消费者的喜好。\n\n尽管珊瑚橘色调占据主导地位，其他颜色如裸橘和樱花粉的仅有10%的使用比例也不容忽视。这两个色调虽然在使用上较为少见，但其独特的气质和柔和的色彩使它们在特定的消费群体中依然具有潜在的市场价值。建议品牌在产品线中尝试推出限量版或季节性产品，使用裸橘和樱花粉，以吸引对新颖和差异化色彩有需求的消费者。\n\n总体来看，未来的美妆趋势可能会继续倾向于鲜艳、生动的色调，尤其是以珊瑚橘为代表的热情色彩。同时，品牌应该在色彩选择上保持一定的多样性，以便能够吸引更广泛的客户群体。在营销推广中，可以借助社交媒体平台，进行颜色搭配的展示，增强消费者的购买欲望。",
        "charts": [
          {
            "chart_type": "pie",
            "chart_title": "使用色彩占比",
            "description": "各色彩在化妆笔记中使用的占比",
            "echarts_option": {
              "tooltip": {
                "trigger": "item",
                "formatter": "{a} <br/>{b}: {c} ({d}%)"
              },
              "legend": {
                "orient": "vertical",
                "left": "left",
                "top": "middle"
              },
              "series": [
                {
                  "name": "使用色彩占比",
                  "type": "pie",
                  "radius": "50%",
                  "center": [
                    "50%",
                    "60%"
                  ],
                  "data": [
                    {
                      "name": "珊瑚橘",
                      "value": 8
                    },
                    {
                      "name": "裸橘",
                      "value": 1
                    },
                    {
                      "name": "樱花粉",
                      "value": 1
                    }
                  ],
                  "label": {
                    "normal": {
                      "show": true,
                      "position": "outside"
                    }
                  },
                  "itemStyle": {
                    "normal": {
                      "borderWidth": 3,
                      "borderColor": "#fff"
                    }
                  }
                }
              ],
              "color": [
                "#ff6b9d",
                "#5f27cd",
                "#00d2d3",
                "#feca57",
                "#ee5a6f",
                "#48dbfb",
                "#ff9ff3",
                "#54a0ff"
              ]
            }
          },
          {
            "chart_type": "bar",
            "chart_title": "色彩使用数量对比",
            "description": "对比不同色彩的使用数量",
            "echarts_option": {
              "tooltip": {
                "trigger": "axis",
                "axisPointer": {
                  "type": "shadow"
                }
              },
              "grid": {
                "left": "3%",
                "right": "4%",
                "bottom": "3%",
                "containLabel": true
              },
              "xAxis": {
                "type": "value",
                "axisLabel": {
                  "formatter": "{value}"
                },
                "axisLine": {
                  "lineStyle": {
                    "color": "#333"
                  }
                }
              },
              "yAxis": {
                "type": "category",
                "data": [
                  "珊瑚橘",
                  "裸橘",
                  "樱花粉"
                ]
              },
              "series": [
                {
                  "name": "色彩使用数量",
                  "type": "bar",
                  "data": [
                    8,
                    1,
                    1
                  ],
                  "barWidth": "60%",
                  "itemStyle": {
                    "color": "#ff6b9d"
                  },
                  "label": {
                    "show": true,
                    "position": "insideRight",
                    "formatter": "{c}"
                  }
                }
              ],
              "color": [
                "#ff6b9d",
                "#5f27cd",
                "#00d2d3",
                "#feca57",
                "#ee5a6f",
                "#48dbfb",
                "#ff9ff3",
                "#54a0ff"
              ]
            }
          }
        ],
        "order": 2
      },
      {
        "section_id": "section-3",
        "title": "关键词分析",
        "content": "在本次关键词分析中，我们对美妆领域的相关词汇进行了深入探讨，发现\"显白\"以10次的出现频率排在最前，这表明消费者对肤色提亮的需求依然强烈，这一趋势在夏季尤为明显。随着社交媒体的盛行，\"显白\"已经成为消费者选购化妆品时的重要考虑因素，指导品牌在产品开发和市场营销中，更加聚焦于这一需求，以提高市场竞争力。\n\n其次，\"不拔干\"和\"日常\"各出现7次，显示出消费者对保湿和日常妆容的重视。\"不拔干\"的高频出现反映了用户在选择底妆产品时希望保持肌肤水润感，避免干燥带来的不适，品牌应注重研发具有良好保湿效果的产品，以提高顾客满意度。而\"日常\"关键词的出现则表明，消费者倾向于选择适合日常生活的自然妆容，品牌可以通过推出轻薄、易上妆的产品来满足这一市场需求。\n\n最后，词频较低的\"自然感\"、\"气质\"和\"水润\"等关键词强调了消费者对妆效的多元化需求，尽管出现次数不高，但这些词汇的存在提示我们，完美的妆容应该包容多样化特点。品牌可考虑在产品宣传中强调这些特性，满足不同消费者的个性化需求，在保证显著效果的同时，也注重提供自然、清透的妆效，以吸引更广泛的客户群体。",
        "charts": [
          {
            "chart_type": "scatter",
            "chart_title": "关键词使用频率分布",
            "description": "显示关键字在笔记中出现的频率",
            "echarts_option": {
              "tooltip": {
                "trigger": "item",
                "formatter": "{b}: {c}"
              },
              "grid": {
                "left": "3%",
                "right": "7%",
                "bottom": "3%",
                "containLabel": true
              },
              "xAxis": {
                "show": false,
                "type": "value",
                "min": 0,
                "max": 10
              },
              "yAxis": {
                "show": false,
                "type": "value",
                "min": 0,
                "max": 10
              },
              "series": [
                {
                  "type": "scatter",
                  "symbolSize": 20,
                  "data": [
                    [
                      4,
                      5,
                      80,
                      "显白"
                    ],
                    [
                      6,
                      6,
                      70,
                      "不拔干"
                    ],
                    [
                      5,
                      7,
                      70,
                      "日常"
                    ],
                    [
                      3,
                      6,
                      10,
                      "自然感"
                    ],
                    [
                      4,
                      7,
                      10,
                      "气质"
                    ],
                    [
                      5,
                      5,
                      10,
                      "水润"
                    ],
                    [
                      2,
                      8,
                      10,
                      "自然清透"
                    ],
                    [
                      7,
                      6,
                      10,
                      "不晕染"
                    ],
                    [
                      8,
                      5,
                      10,
                      "清透"
                    ]
                  ],
                  "label": {
                    "show": true,
                    "position": "top",
                    "formatter": "{b}"
                  },
                  "itemStyle": {
                    "color": "#ff6b9d"
                  }
                }
              ],
              "color": [
                "#ff6b9d",
                "#5f27cd",
                "#00d2d3",
                "#feca57",
                "#ee5a6f",
                "#48dbfb",
                "#ff9ff3",
                "#54a0ff"
              ]
            }
          },
          {
            "chart_type": "bar",
            "chart_title": "关键词数量对比",
            "description": "对比不同关键词的使用数量",
            "echarts_option": {
              "tooltip": {
                "trigger": "axis",
                "axisPointer": {
                  "type": "shadow"
                }
              },
              "grid": {
                "left": "3%",
                "right": "4%",
                "bottom": "3%",
                "containLabel": true
              },
              "xAxis": {
                "type": "category",
                "data": [
                  "显白",
                  "不拔干",
                  "日常",
                  "自然感",
                  "气质",
                  "水润",
                  "自然清透",
                  "不晕染",
                  "清透"
                ],
                "axisLabel": {
                  "show": true,
                  "rotate": 45
                },
                "axisLine": {
                  "show": true
                }
              },
              "yAxis": {
                "type": "value"
              },
              "series": [
                {
                  "name": "关键词数量",
                  "type": "bar",
                  "data": [
                    10,
                    7,
                    7,
                    1,
                    1,
                    1,
                    1,
                    1,
                    1
                  ],
                  "barWidth": "60%",
                  "itemStyle": {
                    "color": {
                      "type": "bar",
                      "colorStops": [
                        {
                          "offset": 0,
                          "color": "#ff6b9d"
                        },
                        {
                          "offset": 1,
                          "color": "#5f27cd"
                        }
                      ]
                    }
                  },
                  "label": {
                    "show": true,
                    "position": "top"
                  }
                }
              ],
              "color": [
                "#ff6b9d",
                "#5f27cd",
                "#00d2d3",
                "#feca57",
                "#ee5a6f",
                "#48dbfb",
                "#ff9ff3",
                "#54a0ff"
              ]
            }
          }
        ],
        "order": 3
      }
    ]
  }
}